{"_path":"/utilities/expression-builder","_dir":"utilities","_draft":false,"_partial":false,"_locale":"","title":"Expression Builder","description":"","body":{"type":"root","children":[{"type":"element","tag":"h1","props":{"id":"expression-builder"},"children":[{"type":"text","value":"Expression Builder"}]},{"type":"element","tag":"h2","props":{"id":"usage"},"children":[{"type":"text","value":"Usage"}]},{"type":"element","tag":"p","props":{},"children":[{"type":"text","value":"Expression builder for Cloudflare "},{"type":"element","tag":"a","props":{"href":"https://developers.cloudflare.com/ruleset-engine/rules-language/","rel":["nofollow"]},"children":[{"type":"text","value":"Rules language"}]},{"type":"text","value":"."}]},{"type":"element","tag":"pre","props":{"className":"language-php shiki shiki-themes github-dark github-light","code":"\nuse Cloudflare\\ExpressionBuilder;\n\n$expression = (new ExpressionBuilder())\n    ->field('ip.src')\n    ->eq('127.0.0.1')\n    ->build();\n\necho $expression;\n\n// ip.src eq 127.0.0.1\n\n","filename":"php","language":"php","meta":"","style":""},"children":[{"type":"element","tag":"code","props":{"__ignoreMap":""},"children":[{"type":"element","tag":"span","props":{"class":"line","line":1},"children":[{"type":"element","tag":"span","props":{"emptyLinePlaceholder":true},"children":[{"type":"text","value":"\n"}]}]},{"type":"element","tag":"span","props":{"class":"line","line":2},"children":[{"type":"element","tag":"span","props":{"style":"--shiki-dark:#F97583;--shiki-default:#D73A49"},"children":[{"type":"text","value":"use"}]},{"type":"element","tag":"span","props":{"style":"--shiki-dark:#79B8FF;--shiki-default:#005CC5"},"children":[{"type":"text","value":" Cloudflare\\ExpressionBuilder"}]},{"type":"element","tag":"span","props":{"style":"--shiki-dark:#E1E4E8;--shiki-default:#24292E"},"children":[{"type":"text","value":";\n"}]}]},{"type":"element","tag":"span","props":{"class":"line","line":3},"children":[{"type":"element","tag":"span","props":{"emptyLinePlaceholder":true},"children":[{"type":"text","value":"\n"}]}]},{"type":"element","tag":"span","props":{"class":"line","line":4},"children":[{"type":"element","tag":"span","props":{"style":"--shiki-dark:#E1E4E8;--shiki-default:#24292E"},"children":[{"type":"text","value":"$expression "}]},{"type":"element","tag":"span","props":{"style":"--shiki-dark:#F97583;--shiki-default:#D73A49"},"children":[{"type":"text","value":"="}]},{"type":"element","tag":"span","props":{"style":"--shiki-dark:#E1E4E8;--shiki-default:#24292E"},"children":[{"type":"text","value":" ("}]},{"type":"element","tag":"span","props":{"style":"--shiki-dark:#F97583;--shiki-default:#D73A49"},"children":[{"type":"text","value":"new"}]},{"type":"element","tag":"span","props":{"style":"--shiki-dark:#79B8FF;--shiki-default:#005CC5"},"children":[{"type":"text","value":" ExpressionBuilder"}]},{"type":"element","tag":"span","props":{"style":"--shiki-dark:#E1E4E8;--shiki-default:#24292E"},"children":[{"type":"text","value":"())\n"}]}]},{"type":"element","tag":"span","props":{"class":"line","line":5},"children":[{"type":"element","tag":"span","props":{"style":"--shiki-dark:#F97583;--shiki-default:#D73A49"},"children":[{"type":"text","value":"    ->"}]},{"type":"element","tag":"span","props":{"style":"--shiki-dark:#B392F0;--shiki-default:#6F42C1"},"children":[{"type":"text","value":"field"}]},{"type":"element","tag":"span","props":{"style":"--shiki-dark:#E1E4E8;--shiki-default:#24292E"},"children":[{"type":"text","value":"("}]},{"type":"element","tag":"span","props":{"style":"--shiki-dark:#9ECBFF;--shiki-default:#032F62"},"children":[{"type":"text","value":"'ip.src'"}]},{"type":"element","tag":"span","props":{"style":"--shiki-dark:#E1E4E8;--shiki-default:#24292E"},"children":[{"type":"text","value":")\n"}]}]},{"type":"element","tag":"span","props":{"class":"line","line":6},"children":[{"type":"element","tag":"span","props":{"style":"--shiki-dark:#F97583;--shiki-default:#D73A49"},"children":[{"type":"text","value":"    ->"}]},{"type":"element","tag":"span","props":{"style":"--shiki-dark:#B392F0;--shiki-default:#6F42C1"},"children":[{"type":"text","value":"eq"}]},{"type":"element","tag":"span","props":{"style":"--shiki-dark:#E1E4E8;--shiki-default:#24292E"},"children":[{"type":"text","value":"("}]},{"type":"element","tag":"span","props":{"style":"--shiki-dark:#9ECBFF;--shiki-default:#032F62"},"children":[{"type":"text","value":"'127.0.0.1'"}]},{"type":"element","tag":"span","props":{"style":"--shiki-dark:#E1E4E8;--shiki-default:#24292E"},"children":[{"type":"text","value":")\n"}]}]},{"type":"element","tag":"span","props":{"class":"line","line":7},"children":[{"type":"element","tag":"span","props":{"style":"--shiki-dark:#F97583;--shiki-default:#D73A49"},"children":[{"type":"text","value":"    ->"}]},{"type":"element","tag":"span","props":{"style":"--shiki-dark:#B392F0;--shiki-default:#6F42C1"},"children":[{"type":"text","value":"build"}]},{"type":"element","tag":"span","props":{"style":"--shiki-dark:#E1E4E8;--shiki-default:#24292E"},"children":[{"type":"text","value":"();\n"}]}]},{"type":"element","tag":"span","props":{"class":"line","line":8},"children":[{"type":"element","tag":"span","props":{"emptyLinePlaceholder":true},"children":[{"type":"text","value":"\n"}]}]},{"type":"element","tag":"span","props":{"class":"line","line":9},"children":[{"type":"element","tag":"span","props":{"style":"--shiki-dark:#79B8FF;--shiki-default:#005CC5"},"children":[{"type":"text","value":"echo"}]},{"type":"element","tag":"span","props":{"style":"--shiki-dark:#E1E4E8;--shiki-default:#24292E"},"children":[{"type":"text","value":" $expression;\n"}]}]},{"type":"element","tag":"span","props":{"class":"line","line":10},"children":[{"type":"element","tag":"span","props":{"emptyLinePlaceholder":true},"children":[{"type":"text","value":"\n"}]}]},{"type":"element","tag":"span","props":{"class":"line","line":11},"children":[{"type":"element","tag":"span","props":{"style":"--shiki-dark:#6A737D;--shiki-default:#6A737D"},"children":[{"type":"text","value":"// ip.src eq 127.0.0.1\n"}]}]}]}]},{"type":"element","tag":"h2","props":{"id":"grouping"},"children":[{"type":"text","value":"Grouping"}]},{"type":"element","tag":"p","props":{},"children":[{"type":"text","value":"The Rules language supports parentheses ("},{"type":"element","tag":"code","props":{"className":[]},"children":[{"type":"text","value":"("}]},{"type":"text","value":","},{"type":"element","tag":"code","props":{"className":[]},"children":[{"type":"text","value":")"}]},{"type":"text","value":") as grouping symbols. Grouping symbols allow you to organize expressions, enforce precedence, and nest expressions."}]},{"type":"element","tag":"pre","props":{"className":"language-php shiki shiki-themes github-dark github-light","code":"\nuse Cloudflare\\ExpressionBuilder;\n\n$expression = (new ExpressionBuilder())\n    ->field('ip.src')\n    ->eq('127.0.0.1')\n    ->or()\n    ->group(function(ExpressionBuilder $builder){\n        $builder->not()->field('ssl')->or()->field('ip.src.country')->eq('GB');\n    })\n    ->build();\n\necho $expression;\n\n// ip.src eq 127.0.0.1 or (not ssl or ip.src.country eq \"GB\")\n\n","filename":"php","language":"php","meta":"","style":""},"children":[{"type":"element","tag":"code","props":{"__ignoreMap":""},"children":[{"type":"element","tag":"span","props":{"class":"line","line":1},"children":[{"type":"element","tag":"span","props":{"emptyLinePlaceholder":true},"children":[{"type":"text","value":"\n"}]}]},{"type":"element","tag":"span","props":{"class":"line","line":2},"children":[{"type":"element","tag":"span","props":{"style":"--shiki-dark:#F97583;--shiki-default:#D73A49"},"children":[{"type":"text","value":"use"}]},{"type":"element","tag":"span","props":{"style":"--shiki-dark:#79B8FF;--shiki-default:#005CC5"},"children":[{"type":"text","value":" Cloudflare\\ExpressionBuilder"}]},{"type":"element","tag":"span","props":{"style":"--shiki-dark:#E1E4E8;--shiki-default:#24292E"},"children":[{"type":"text","value":";\n"}]}]},{"type":"element","tag":"span","props":{"class":"line","line":3},"children":[{"type":"element","tag":"span","props":{"emptyLinePlaceholder":true},"children":[{"type":"text","value":"\n"}]}]},{"type":"element","tag":"span","props":{"class":"line","line":4},"children":[{"type":"element","tag":"span","props":{"style":"--shiki-dark:#E1E4E8;--shiki-default:#24292E"},"children":[{"type":"text","value":"$expression "}]},{"type":"element","tag":"span","props":{"style":"--shiki-dark:#F97583;--shiki-default:#D73A49"},"children":[{"type":"text","value":"="}]},{"type":"element","tag":"span","props":{"style":"--shiki-dark:#E1E4E8;--shiki-default:#24292E"},"children":[{"type":"text","value":" ("}]},{"type":"element","tag":"span","props":{"style":"--shiki-dark:#F97583;--shiki-default:#D73A49"},"children":[{"type":"text","value":"new"}]},{"type":"element","tag":"span","props":{"style":"--shiki-dark:#79B8FF;--shiki-default:#005CC5"},"children":[{"type":"text","value":" ExpressionBuilder"}]},{"type":"element","tag":"span","props":{"style":"--shiki-dark:#E1E4E8;--shiki-default:#24292E"},"children":[{"type":"text","value":"())\n"}]}]},{"type":"element","tag":"span","props":{"class":"line","line":5},"children":[{"type":"element","tag":"span","props":{"style":"--shiki-dark:#F97583;--shiki-default:#D73A49"},"children":[{"type":"text","value":"    ->"}]},{"type":"element","tag":"span","props":{"style":"--shiki-dark:#B392F0;--shiki-default:#6F42C1"},"children":[{"type":"text","value":"field"}]},{"type":"element","tag":"span","props":{"style":"--shiki-dark:#E1E4E8;--shiki-default:#24292E"},"children":[{"type":"text","value":"("}]},{"type":"element","tag":"span","props":{"style":"--shiki-dark:#9ECBFF;--shiki-default:#032F62"},"children":[{"type":"text","value":"'ip.src'"}]},{"type":"element","tag":"span","props":{"style":"--shiki-dark:#E1E4E8;--shiki-default:#24292E"},"children":[{"type":"text","value":")\n"}]}]},{"type":"element","tag":"span","props":{"class":"line","line":6},"children":[{"type":"element","tag":"span","props":{"style":"--shiki-dark:#F97583;--shiki-default:#D73A49"},"children":[{"type":"text","value":"    ->"}]},{"type":"element","tag":"span","props":{"style":"--shiki-dark:#B392F0;--shiki-default:#6F42C1"},"children":[{"type":"text","value":"eq"}]},{"type":"element","tag":"span","props":{"style":"--shiki-dark:#E1E4E8;--shiki-default:#24292E"},"children":[{"type":"text","value":"("}]},{"type":"element","tag":"span","props":{"style":"--shiki-dark:#9ECBFF;--shiki-default:#032F62"},"children":[{"type":"text","value":"'127.0.0.1'"}]},{"type":"element","tag":"span","props":{"style":"--shiki-dark:#E1E4E8;--shiki-default:#24292E"},"children":[{"type":"text","value":")\n"}]}]},{"type":"element","tag":"span","props":{"class":"line","line":7},"children":[{"type":"element","tag":"span","props":{"style":"--shiki-dark:#F97583;--shiki-default:#D73A49"},"children":[{"type":"text","value":"    ->"}]},{"type":"element","tag":"span","props":{"style":"--shiki-dark:#B392F0;--shiki-default:#6F42C1"},"children":[{"type":"text","value":"or"}]},{"type":"element","tag":"span","props":{"style":"--shiki-dark:#E1E4E8;--shiki-default:#24292E"},"children":[{"type":"text","value":"()\n"}]}]},{"type":"element","tag":"span","props":{"class":"line","line":8},"children":[{"type":"element","tag":"span","props":{"style":"--shiki-dark:#F97583;--shiki-default:#D73A49"},"children":[{"type":"text","value":"    ->"}]},{"type":"element","tag":"span","props":{"style":"--shiki-dark:#B392F0;--shiki-default:#6F42C1"},"children":[{"type":"text","value":"group"}]},{"type":"element","tag":"span","props":{"style":"--shiki-dark:#E1E4E8;--shiki-default:#24292E"},"children":[{"type":"text","value":"("}]},{"type":"element","tag":"span","props":{"style":"--shiki-dark:#F97583;--shiki-default:#D73A49"},"children":[{"type":"text","value":"function"}]},{"type":"element","tag":"span","props":{"style":"--shiki-dark:#E1E4E8;--shiki-default:#24292E"},"children":[{"type":"text","value":"("}]},{"type":"element","tag":"span","props":{"style":"--shiki-dark:#79B8FF;--shiki-default:#005CC5"},"children":[{"type":"text","value":"ExpressionBuilder"}]},{"type":"element","tag":"span","props":{"style":"--shiki-dark:#E1E4E8;--shiki-default:#24292E"},"children":[{"type":"text","value":" $builder){\n"}]}]},{"type":"element","tag":"span","props":{"class":"line","line":9},"children":[{"type":"element","tag":"span","props":{"style":"--shiki-dark:#E1E4E8;--shiki-default:#24292E"},"children":[{"type":"text","value":"        $builder"}]},{"type":"element","tag":"span","props":{"style":"--shiki-dark:#F97583;--shiki-default:#D73A49"},"children":[{"type":"text","value":"->"}]},{"type":"element","tag":"span","props":{"style":"--shiki-dark:#B392F0;--shiki-default:#6F42C1"},"children":[{"type":"text","value":"not"}]},{"type":"element","tag":"span","props":{"style":"--shiki-dark:#E1E4E8;--shiki-default:#24292E"},"children":[{"type":"text","value":"()"}]},{"type":"element","tag":"span","props":{"style":"--shiki-dark:#F97583;--shiki-default:#D73A49"},"children":[{"type":"text","value":"->"}]},{"type":"element","tag":"span","props":{"style":"--shiki-dark:#B392F0;--shiki-default:#6F42C1"},"children":[{"type":"text","value":"field"}]},{"type":"element","tag":"span","props":{"style":"--shiki-dark:#E1E4E8;--shiki-default:#24292E"},"children":[{"type":"text","value":"("}]},{"type":"element","tag":"span","props":{"style":"--shiki-dark:#9ECBFF;--shiki-default:#032F62"},"children":[{"type":"text","value":"'ssl'"}]},{"type":"element","tag":"span","props":{"style":"--shiki-dark:#E1E4E8;--shiki-default:#24292E"},"children":[{"type":"text","value":")"}]},{"type":"element","tag":"span","props":{"style":"--shiki-dark:#F97583;--shiki-default:#D73A49"},"children":[{"type":"text","value":"->"}]},{"type":"element","tag":"span","props":{"style":"--shiki-dark:#B392F0;--shiki-default:#6F42C1"},"children":[{"type":"text","value":"or"}]},{"type":"element","tag":"span","props":{"style":"--shiki-dark:#E1E4E8;--shiki-default:#24292E"},"children":[{"type":"text","value":"()"}]},{"type":"element","tag":"span","props":{"style":"--shiki-dark:#F97583;--shiki-default:#D73A49"},"children":[{"type":"text","value":"->"}]},{"type":"element","tag":"span","props":{"style":"--shiki-dark:#B392F0;--shiki-default:#6F42C1"},"children":[{"type":"text","value":"field"}]},{"type":"element","tag":"span","props":{"style":"--shiki-dark:#E1E4E8;--shiki-default:#24292E"},"children":[{"type":"text","value":"("}]},{"type":"element","tag":"span","props":{"style":"--shiki-dark:#9ECBFF;--shiki-default:#032F62"},"children":[{"type":"text","value":"'ip.src.country'"}]},{"type":"element","tag":"span","props":{"style":"--shiki-dark:#E1E4E8;--shiki-default:#24292E"},"children":[{"type":"text","value":")"}]},{"type":"element","tag":"span","props":{"style":"--shiki-dark:#F97583;--shiki-default:#D73A49"},"children":[{"type":"text","value":"->"}]},{"type":"element","tag":"span","props":{"style":"--shiki-dark:#B392F0;--shiki-default:#6F42C1"},"children":[{"type":"text","value":"eq"}]},{"type":"element","tag":"span","props":{"style":"--shiki-dark:#E1E4E8;--shiki-default:#24292E"},"children":[{"type":"text","value":"("}]},{"type":"element","tag":"span","props":{"style":"--shiki-dark:#9ECBFF;--shiki-default:#032F62"},"children":[{"type":"text","value":"'GB'"}]},{"type":"element","tag":"span","props":{"style":"--shiki-dark:#E1E4E8;--shiki-default:#24292E"},"children":[{"type":"text","value":");\n"}]}]},{"type":"element","tag":"span","props":{"class":"line","line":10},"children":[{"type":"element","tag":"span","props":{"style":"--shiki-dark:#E1E4E8;--shiki-default:#24292E"},"children":[{"type":"text","value":"    })\n"}]}]},{"type":"element","tag":"span","props":{"class":"line","line":11},"children":[{"type":"element","tag":"span","props":{"style":"--shiki-dark:#F97583;--shiki-default:#D73A49"},"children":[{"type":"text","value":"    ->"}]},{"type":"element","tag":"span","props":{"style":"--shiki-dark:#B392F0;--shiki-default:#6F42C1"},"children":[{"type":"text","value":"build"}]},{"type":"element","tag":"span","props":{"style":"--shiki-dark:#E1E4E8;--shiki-default:#24292E"},"children":[{"type":"text","value":"();\n"}]}]},{"type":"element","tag":"span","props":{"class":"line","line":12},"children":[{"type":"element","tag":"span","props":{"emptyLinePlaceholder":true},"children":[{"type":"text","value":"\n"}]}]},{"type":"element","tag":"span","props":{"class":"line","line":13},"children":[{"type":"element","tag":"span","props":{"style":"--shiki-dark:#79B8FF;--shiki-default:#005CC5"},"children":[{"type":"text","value":"echo"}]},{"type":"element","tag":"span","props":{"style":"--shiki-dark:#E1E4E8;--shiki-default:#24292E"},"children":[{"type":"text","value":" $expression;\n"}]}]},{"type":"element","tag":"span","props":{"class":"line","line":14},"children":[{"type":"element","tag":"span","props":{"emptyLinePlaceholder":true},"children":[{"type":"text","value":"\n"}]}]},{"type":"element","tag":"span","props":{"class":"line","line":15},"children":[{"type":"element","tag":"span","props":{"style":"--shiki-dark:#6A737D;--shiki-default:#6A737D"},"children":[{"type":"text","value":"// ip.src eq 127.0.0.1 or (not ssl or ip.src.country eq \"GB\")\n"}]}]}]}]},{"type":"element","tag":"h2","props":{"id":"functions"},"children":[{"type":"text","value":"Functions"}]},{"type":"element","tag":"p","props":{},"children":[{"type":"text","value":"The Cloudflare Rules language provides functions for manipulating and validating values in an expression."}]},{"type":"element","tag":"pre","props":{"className":"language-php shiki shiki-themes github-dark github-light","code":"\nuse Cloudflare\\ExpressionBuilder;\n\n$expression = (new ExpressionBuilder())\n    ->addFunction('lower', 'ip.src.country')\n    ->eq('127.0.0.1')\n    ->build();\n\necho $expression;\n\n// lower(ip.src.country) eq \"gb\"\n\n","filename":"php","language":"php","meta":"","style":""},"children":[{"type":"element","tag":"code","props":{"__ignoreMap":""},"children":[{"type":"element","tag":"span","props":{"class":"line","line":1},"children":[{"type":"element","tag":"span","props":{"emptyLinePlaceholder":true},"children":[{"type":"text","value":"\n"}]}]},{"type":"element","tag":"span","props":{"class":"line","line":2},"children":[{"type":"element","tag":"span","props":{"style":"--shiki-dark:#F97583;--shiki-default:#D73A49"},"children":[{"type":"text","value":"use"}]},{"type":"element","tag":"span","props":{"style":"--shiki-dark:#79B8FF;--shiki-default:#005CC5"},"children":[{"type":"text","value":" Cloudflare\\ExpressionBuilder"}]},{"type":"element","tag":"span","props":{"style":"--shiki-dark:#E1E4E8;--shiki-default:#24292E"},"children":[{"type":"text","value":";\n"}]}]},{"type":"element","tag":"span","props":{"class":"line","line":3},"children":[{"type":"element","tag":"span","props":{"emptyLinePlaceholder":true},"children":[{"type":"text","value":"\n"}]}]},{"type":"element","tag":"span","props":{"class":"line","line":4},"children":[{"type":"element","tag":"span","props":{"style":"--shiki-dark:#E1E4E8;--shiki-default:#24292E"},"children":[{"type":"text","value":"$expression "}]},{"type":"element","tag":"span","props":{"style":"--shiki-dark:#F97583;--shiki-default:#D73A49"},"children":[{"type":"text","value":"="}]},{"type":"element","tag":"span","props":{"style":"--shiki-dark:#E1E4E8;--shiki-default:#24292E"},"children":[{"type":"text","value":" ("}]},{"type":"element","tag":"span","props":{"style":"--shiki-dark:#F97583;--shiki-default:#D73A49"},"children":[{"type":"text","value":"new"}]},{"type":"element","tag":"span","props":{"style":"--shiki-dark:#79B8FF;--shiki-default:#005CC5"},"children":[{"type":"text","value":" ExpressionBuilder"}]},{"type":"element","tag":"span","props":{"style":"--shiki-dark:#E1E4E8;--shiki-default:#24292E"},"children":[{"type":"text","value":"())\n"}]}]},{"type":"element","tag":"span","props":{"class":"line","line":5},"children":[{"type":"element","tag":"span","props":{"style":"--shiki-dark:#F97583;--shiki-default:#D73A49"},"children":[{"type":"text","value":"    ->"}]},{"type":"element","tag":"span","props":{"style":"--shiki-dark:#B392F0;--shiki-default:#6F42C1"},"children":[{"type":"text","value":"addFunction"}]},{"type":"element","tag":"span","props":{"style":"--shiki-dark:#E1E4E8;--shiki-default:#24292E"},"children":[{"type":"text","value":"("}]},{"type":"element","tag":"span","props":{"style":"--shiki-dark:#9ECBFF;--shiki-default:#032F62"},"children":[{"type":"text","value":"'lower'"}]},{"type":"element","tag":"span","props":{"style":"--shiki-dark:#E1E4E8;--shiki-default:#24292E"},"children":[{"type":"text","value":", "}]},{"type":"element","tag":"span","props":{"style":"--shiki-dark:#9ECBFF;--shiki-default:#032F62"},"children":[{"type":"text","value":"'ip.src.country'"}]},{"type":"element","tag":"span","props":{"style":"--shiki-dark:#E1E4E8;--shiki-default:#24292E"},"children":[{"type":"text","value":")\n"}]}]},{"type":"element","tag":"span","props":{"class":"line","line":6},"children":[{"type":"element","tag":"span","props":{"style":"--shiki-dark:#F97583;--shiki-default:#D73A49"},"children":[{"type":"text","value":"    ->"}]},{"type":"element","tag":"span","props":{"style":"--shiki-dark:#B392F0;--shiki-default:#6F42C1"},"children":[{"type":"text","value":"eq"}]},{"type":"element","tag":"span","props":{"style":"--shiki-dark:#E1E4E8;--shiki-default:#24292E"},"children":[{"type":"text","value":"("}]},{"type":"element","tag":"span","props":{"style":"--shiki-dark:#9ECBFF;--shiki-default:#032F62"},"children":[{"type":"text","value":"'127.0.0.1'"}]},{"type":"element","tag":"span","props":{"style":"--shiki-dark:#E1E4E8;--shiki-default:#24292E"},"children":[{"type":"text","value":")\n"}]}]},{"type":"element","tag":"span","props":{"class":"line","line":7},"children":[{"type":"element","tag":"span","props":{"style":"--shiki-dark:#F97583;--shiki-default:#D73A49"},"children":[{"type":"text","value":"    ->"}]},{"type":"element","tag":"span","props":{"style":"--shiki-dark:#B392F0;--shiki-default:#6F42C1"},"children":[{"type":"text","value":"build"}]},{"type":"element","tag":"span","props":{"style":"--shiki-dark:#E1E4E8;--shiki-default:#24292E"},"children":[{"type":"text","value":"();\n"}]}]},{"type":"element","tag":"span","props":{"class":"line","line":8},"children":[{"type":"element","tag":"span","props":{"emptyLinePlaceholder":true},"children":[{"type":"text","value":"\n"}]}]},{"type":"element","tag":"span","props":{"class":"line","line":9},"children":[{"type":"element","tag":"span","props":{"style":"--shiki-dark:#79B8FF;--shiki-default:#005CC5"},"children":[{"type":"text","value":"echo"}]},{"type":"element","tag":"span","props":{"style":"--shiki-dark:#E1E4E8;--shiki-default:#24292E"},"children":[{"type":"text","value":" $expression;\n"}]}]},{"type":"element","tag":"span","props":{"class":"line","line":10},"children":[{"type":"element","tag":"span","props":{"emptyLinePlaceholder":true},"children":[{"type":"text","value":"\n"}]}]},{"type":"element","tag":"span","props":{"class":"line","line":11},"children":[{"type":"element","tag":"span","props":{"style":"--shiki-dark:#6A737D;--shiki-default:#6A737D"},"children":[{"type":"text","value":"// lower(ip.src.country) eq \"gb\"\n"}]}]}]}]},{"type":"element","tag":"h2","props":{"id":"raw-expressions"},"children":[{"type":"text","value":"Raw expressions"}]},{"type":"element","tag":"pre","props":{"className":"language-php shiki shiki-themes github-dark github-light","code":"\nuse Cloudflare\\ExpressionBuilder;\n\n$expression = (new ExpressionBuilder())\n    ->addExpression('ip.src.country', 'eq', 'GB')\n    ->build();\n\necho $expression;\n\n// ip.src.country eq \"GB\"\n\n","filename":"php","language":"php","meta":"","style":""},"children":[{"type":"element","tag":"code","props":{"__ignoreMap":""},"children":[{"type":"element","tag":"span","props":{"class":"line","line":1},"children":[{"type":"element","tag":"span","props":{"emptyLinePlaceholder":true},"children":[{"type":"text","value":"\n"}]}]},{"type":"element","tag":"span","props":{"class":"line","line":2},"children":[{"type":"element","tag":"span","props":{"style":"--shiki-dark:#F97583;--shiki-default:#D73A49"},"children":[{"type":"text","value":"use"}]},{"type":"element","tag":"span","props":{"style":"--shiki-dark:#79B8FF;--shiki-default:#005CC5"},"children":[{"type":"text","value":" Cloudflare\\ExpressionBuilder"}]},{"type":"element","tag":"span","props":{"style":"--shiki-dark:#E1E4E8;--shiki-default:#24292E"},"children":[{"type":"text","value":";\n"}]}]},{"type":"element","tag":"span","props":{"class":"line","line":3},"children":[{"type":"element","tag":"span","props":{"emptyLinePlaceholder":true},"children":[{"type":"text","value":"\n"}]}]},{"type":"element","tag":"span","props":{"class":"line","line":4},"children":[{"type":"element","tag":"span","props":{"style":"--shiki-dark:#E1E4E8;--shiki-default:#24292E"},"children":[{"type":"text","value":"$expression "}]},{"type":"element","tag":"span","props":{"style":"--shiki-dark:#F97583;--shiki-default:#D73A49"},"children":[{"type":"text","value":"="}]},{"type":"element","tag":"span","props":{"style":"--shiki-dark:#E1E4E8;--shiki-default:#24292E"},"children":[{"type":"text","value":" ("}]},{"type":"element","tag":"span","props":{"style":"--shiki-dark:#F97583;--shiki-default:#D73A49"},"children":[{"type":"text","value":"new"}]},{"type":"element","tag":"span","props":{"style":"--shiki-dark:#79B8FF;--shiki-default:#005CC5"},"children":[{"type":"text","value":" ExpressionBuilder"}]},{"type":"element","tag":"span","props":{"style":"--shiki-dark:#E1E4E8;--shiki-default:#24292E"},"children":[{"type":"text","value":"())\n"}]}]},{"type":"element","tag":"span","props":{"class":"line","line":5},"children":[{"type":"element","tag":"span","props":{"style":"--shiki-dark:#F97583;--shiki-default:#D73A49"},"children":[{"type":"text","value":"    ->"}]},{"type":"element","tag":"span","props":{"style":"--shiki-dark:#B392F0;--shiki-default:#6F42C1"},"children":[{"type":"text","value":"addExpression"}]},{"type":"element","tag":"span","props":{"style":"--shiki-dark:#E1E4E8;--shiki-default:#24292E"},"children":[{"type":"text","value":"("}]},{"type":"element","tag":"span","props":{"style":"--shiki-dark:#9ECBFF;--shiki-default:#032F62"},"children":[{"type":"text","value":"'ip.src.country'"}]},{"type":"element","tag":"span","props":{"style":"--shiki-dark:#E1E4E8;--shiki-default:#24292E"},"children":[{"type":"text","value":", "}]},{"type":"element","tag":"span","props":{"style":"--shiki-dark:#9ECBFF;--shiki-default:#032F62"},"children":[{"type":"text","value":"'eq'"}]},{"type":"element","tag":"span","props":{"style":"--shiki-dark:#E1E4E8;--shiki-default:#24292E"},"children":[{"type":"text","value":", "}]},{"type":"element","tag":"span","props":{"style":"--shiki-dark:#9ECBFF;--shiki-default:#032F62"},"children":[{"type":"text","value":"'GB'"}]},{"type":"element","tag":"span","props":{"style":"--shiki-dark:#E1E4E8;--shiki-default:#24292E"},"children":[{"type":"text","value":")\n"}]}]},{"type":"element","tag":"span","props":{"class":"line","line":6},"children":[{"type":"element","tag":"span","props":{"style":"--shiki-dark:#F97583;--shiki-default:#D73A49"},"children":[{"type":"text","value":"    ->"}]},{"type":"element","tag":"span","props":{"style":"--shiki-dark:#B392F0;--shiki-default:#6F42C1"},"children":[{"type":"text","value":"build"}]},{"type":"element","tag":"span","props":{"style":"--shiki-dark:#E1E4E8;--shiki-default:#24292E"},"children":[{"type":"text","value":"();\n"}]}]},{"type":"element","tag":"span","props":{"class":"line","line":7},"children":[{"type":"element","tag":"span","props":{"emptyLinePlaceholder":true},"children":[{"type":"text","value":"\n"}]}]},{"type":"element","tag":"span","props":{"class":"line","line":8},"children":[{"type":"element","tag":"span","props":{"style":"--shiki-dark:#79B8FF;--shiki-default:#005CC5"},"children":[{"type":"text","value":"echo"}]},{"type":"element","tag":"span","props":{"style":"--shiki-dark:#E1E4E8;--shiki-default:#24292E"},"children":[{"type":"text","value":" $expression;\n"}]}]},{"type":"element","tag":"span","props":{"class":"line","line":9},"children":[{"type":"element","tag":"span","props":{"emptyLinePlaceholder":true},"children":[{"type":"text","value":"\n"}]}]},{"type":"element","tag":"span","props":{"class":"line","line":10},"children":[{"type":"element","tag":"span","props":{"style":"--shiki-dark:#6A737D;--shiki-default:#6A737D"},"children":[{"type":"text","value":"// ip.src.country eq \"GB\"\n"}]}]}]}]},{"type":"element","tag":"p","props":{},"children":[{"type":"element","tag":"code","props":{"className":[]},"children":[{"type":"text","value":"ExpressionBuilder"}]},{"type":"text","value":" implements "},{"type":"element","tag":"code","props":{"className":[]},"children":[{"type":"text","value":"Stringable"}]},{"type":"text","value":" so you can simply do:"}]},{"type":"element","tag":"pre","props":{"className":"language-php shiki shiki-themes github-dark github-light","code":"\nuse Cloudflare\\ExpressionBuilder;\n\n$expression = (string) (new ExpressionBuilder())\n    ->addExpression('ip.src.country', 'eq', 'GB');\n\necho $expression;\n\n// ip.src.country eq \"GB\"\n\n","filename":"php","language":"php","meta":"","style":""},"children":[{"type":"element","tag":"code","props":{"__ignoreMap":""},"children":[{"type":"element","tag":"span","props":{"class":"line","line":1},"children":[{"type":"element","tag":"span","props":{"emptyLinePlaceholder":true},"children":[{"type":"text","value":"\n"}]}]},{"type":"element","tag":"span","props":{"class":"line","line":2},"children":[{"type":"element","tag":"span","props":{"style":"--shiki-dark:#F97583;--shiki-default:#D73A49"},"children":[{"type":"text","value":"use"}]},{"type":"element","tag":"span","props":{"style":"--shiki-dark:#79B8FF;--shiki-default:#005CC5"},"children":[{"type":"text","value":" Cloudflare\\ExpressionBuilder"}]},{"type":"element","tag":"span","props":{"style":"--shiki-dark:#E1E4E8;--shiki-default:#24292E"},"children":[{"type":"text","value":";\n"}]}]},{"type":"element","tag":"span","props":{"class":"line","line":3},"children":[{"type":"element","tag":"span","props":{"emptyLinePlaceholder":true},"children":[{"type":"text","value":"\n"}]}]},{"type":"element","tag":"span","props":{"class":"line","line":4},"children":[{"type":"element","tag":"span","props":{"style":"--shiki-dark:#E1E4E8;--shiki-default:#24292E"},"children":[{"type":"text","value":"$expression "}]},{"type":"element","tag":"span","props":{"style":"--shiki-dark:#F97583;--shiki-default:#D73A49"},"children":[{"type":"text","value":"="}]},{"type":"element","tag":"span","props":{"style":"--shiki-dark:#E1E4E8;--shiki-default:#24292E"},"children":[{"type":"text","value":" ("}]},{"type":"element","tag":"span","props":{"style":"--shiki-dark:#F97583;--shiki-default:#D73A49"},"children":[{"type":"text","value":"string"}]},{"type":"element","tag":"span","props":{"style":"--shiki-dark:#E1E4E8;--shiki-default:#24292E"},"children":[{"type":"text","value":") ("}]},{"type":"element","tag":"span","props":{"style":"--shiki-dark:#F97583;--shiki-default:#D73A49"},"children":[{"type":"text","value":"new"}]},{"type":"element","tag":"span","props":{"style":"--shiki-dark:#79B8FF;--shiki-default:#005CC5"},"children":[{"type":"text","value":" ExpressionBuilder"}]},{"type":"element","tag":"span","props":{"style":"--shiki-dark:#E1E4E8;--shiki-default:#24292E"},"children":[{"type":"text","value":"())\n"}]}]},{"type":"element","tag":"span","props":{"class":"line","line":5},"children":[{"type":"element","tag":"span","props":{"style":"--shiki-dark:#F97583;--shiki-default:#D73A49"},"children":[{"type":"text","value":"    ->"}]},{"type":"element","tag":"span","props":{"style":"--shiki-dark:#B392F0;--shiki-default:#6F42C1"},"children":[{"type":"text","value":"addExpression"}]},{"type":"element","tag":"span","props":{"style":"--shiki-dark:#E1E4E8;--shiki-default:#24292E"},"children":[{"type":"text","value":"("}]},{"type":"element","tag":"span","props":{"style":"--shiki-dark:#9ECBFF;--shiki-default:#032F62"},"children":[{"type":"text","value":"'ip.src.country'"}]},{"type":"element","tag":"span","props":{"style":"--shiki-dark:#E1E4E8;--shiki-default:#24292E"},"children":[{"type":"text","value":", "}]},{"type":"element","tag":"span","props":{"style":"--shiki-dark:#9ECBFF;--shiki-default:#032F62"},"children":[{"type":"text","value":"'eq'"}]},{"type":"element","tag":"span","props":{"style":"--shiki-dark:#E1E4E8;--shiki-default:#24292E"},"children":[{"type":"text","value":", "}]},{"type":"element","tag":"span","props":{"style":"--shiki-dark:#9ECBFF;--shiki-default:#032F62"},"children":[{"type":"text","value":"'GB'"}]},{"type":"element","tag":"span","props":{"style":"--shiki-dark:#E1E4E8;--shiki-default:#24292E"},"children":[{"type":"text","value":");\n"}]}]},{"type":"element","tag":"span","props":{"class":"line","line":6},"children":[{"type":"element","tag":"span","props":{"emptyLinePlaceholder":true},"children":[{"type":"text","value":"\n"}]}]},{"type":"element","tag":"span","props":{"class":"line","line":7},"children":[{"type":"element","tag":"span","props":{"style":"--shiki-dark:#79B8FF;--shiki-default:#005CC5"},"children":[{"type":"text","value":"echo"}]},{"type":"element","tag":"span","props":{"style":"--shiki-dark:#E1E4E8;--shiki-default:#24292E"},"children":[{"type":"text","value":" $expression;\n"}]}]},{"type":"element","tag":"span","props":{"class":"line","line":8},"children":[{"type":"element","tag":"span","props":{"emptyLinePlaceholder":true},"children":[{"type":"text","value":"\n"}]}]},{"type":"element","tag":"span","props":{"class":"line","line":9},"children":[{"type":"element","tag":"span","props":{"style":"--shiki-dark:#6A737D;--shiki-default:#6A737D"},"children":[{"type":"text","value":"// ip.src.country eq \"GB\"\n"}]}]}]}]},{"type":"element","tag":"style","props":{},"children":[{"type":"text","value":"html .dark .shiki span {color: var(--shiki-dark);background: var(--shiki-dark-bg);font-style: var(--shiki-dark-font-style);font-weight: var(--shiki-dark-font-weight);text-decoration: var(--shiki-dark-text-decoration);}html.dark .shiki span {color: var(--shiki-dark);background: var(--shiki-dark-bg);font-style: var(--shiki-dark-font-style);font-weight: var(--shiki-dark-font-weight);text-decoration: var(--shiki-dark-text-decoration);}html .default .shiki span {color: var(--shiki-default);background: var(--shiki-default-bg);font-style: var(--shiki-default-font-style);font-weight: var(--shiki-default-font-weight);text-decoration: var(--shiki-default-text-decoration);}html .shiki span {color: var(--shiki-default);background: var(--shiki-default-bg);font-style: var(--shiki-default-font-style);font-weight: var(--shiki-default-font-weight);text-decoration: var(--shiki-default-text-decoration);}"}]}],"toc":{"title":"","searchDepth":2,"depth":2,"links":[{"id":"usage","depth":2,"text":"Usage"},{"id":"grouping","depth":2,"text":"Grouping"},{"id":"functions","depth":2,"text":"Functions"},{"id":"raw-expressions","depth":2,"text":"Raw expressions"}]}},"_type":"markdown","_id":"content:3.utilities:2.expression-builder.md","_source":"content","_file":"3.utilities/2.expression-builder.md","_stem":"3.utilities/2.expression-builder","_extension":"md"}